pdt_client
